gsl_331/__init__.py
gsl_331/core.py
gsl_331-1.0.1.dist-info/licenses/LICENSE
gsl_331-1.0.1.dist-info/METADATA
gsl_331-1.0.1.dist-info/WHEEL
gsl_331-1.0.1.dist-info/top_level.txt
gsl_331-1.0.1.dist-info/RECORD
